[
  {
    "title": "Legal affairs of the first Donald Trump presidency",
    "timestamp": "2020-11-09T08:57:12+00:00",
    "added": [
      "",
      "== Trump 2020 Campaign-related lawsuits by state ==",
      "{{update section|date=Nov 9 2020}}",
      "=== New Jersey ===",
      "* Donald J. Trump for President v. Way",
      "=== Pennsylvania ===",
      "* Republican Party of Pennsylvania v. Boockvar, 20-542; Scarnati v. Pennsylvania Democratic Party, 20-574",
      "* Donald J. Trump for President Inc. v. Kathy Boockvar and County Boards of Elections, 602 MD 2020",
      "* Philadelphia County Canvassing Observation Appeal, 1094 CD 20",
      "* Donald J. Trump for President Inc. v. Philadelphia County Board of Elections, 20-5533",
      "* Hamm, Kelly, Allred, Horner, Connor and Hauser v. Boockvar, 600 MD 2020",
      "=== Michigan ===",
      "* Donald J. Trump and Eric Ostergren v. Jocelyn Benson, 20-000225-MZ",
      "=== Georgia ===",
      "* In Re: Enforcement of Election Laws and Securing Ballots Cast or Received after 7:00pm on November 3, 2020, SPCV20-00982",
      "=== Wisconsin ===",
      "* Pierson v. Stepien, 20-CV-9266"
    ],
    "deleted": []
  },
  {
    "title": "Legal affairs of the first Donald Trump presidency",
    "timestamp": "2020-11-27T22:49:00+00:00",
    "added": [
      "{{pp-protected|reason=Persistent addition of [[WP:INTREF|unsourced or poorly sourced content]]|small=yes}}"
    ],
    "deleted": []
  }
]