[
  {
    "title": "2022 United States Senate elections in California",
    "timestamp": "2020-11-04T04:35:46+00:00",
    "added": [],
    "deleted": [
      "Anthony Williams - Retired Assistant Fire Chief Los Angeles County Fire Department",
      ""
    ]
  },
  {
    "title": "2022 United States Senate elections in California",
    "timestamp": "2020-11-26T16:06:41+00:00",
    "added": [
      "",
      "==Primary==",
      "===Polling==="
    ],
    "deleted": []
  },
  {
    "title": "2022 United States Senate elections in California",
    "timestamp": "2020-11-27T20:56:59+00:00",
    "added": [],
    "deleted": [
      "",
      "====Potential====",
      "",
      "===The Integrity Party===",
      "====Declared====",
      "* Marc Roth, candidate pending party certification."
    ]
  },
  {
    "title": "2022 United States Senate elections in California",
    "timestamp": "2020-11-28T03:52:21+00:00",
    "added": [
      "",
      "===The Integrity Party===",
      "====Declared====",
      "* Marc Roth, 2019 Mayoral Candidate San Francisco and 2020 Independent candidate for President."
    ],
    "deleted": []
  }
]