[
  {
    "title": "Sam Liccardo",
    "timestamp": "2021-10-25T00:58:50+00:00",
    "added": [
      "",
      "https://sanjosespotlight.com/san-jose-awarded-city-contracts-to-liccardo-ally-whistleblower-claims-revolution-foods/"
    ],
    "deleted": []
  },
  {
    "title": "Sam Liccardo",
    "timestamp": "2021-10-25T01:00:45+00:00",
    "added": [],
    "deleted": [
      "",
      "===Pandemic Response and Allegations of Corruption===",
      "",
      "On October 24, 2021, San Jose Spotlight published an article outlining allegations from a whistleblower related to misuse of Coronavirus Relief Funds and kickbacks to organizations that have personal relationships with Liccardo.  His wife is the Executive Director of one of the organizations that was paid over $4 million dollars from the City of San Jose while Liccardo was in office.",
      "",
      "https://sanjosespotlight.com/san-jose-awarded-city-contracts-to-liccardo-ally-whistleblower-claims-revolution-foods/"
    ]
  }
]