[
  {
    "title": "Pat Quinn (politician)",
    "timestamp": "2020-10-04T18:09:23+00:00",
    "added": [
      "",
      "He served on the [[local school council]] of Sayre Magnet School on Chicago's West Side.<ref name=\"NWItimes14oct\"/>"
    ],
    "deleted": []
  },
  {
    "title": "Pat Quinn (politician)",
    "timestamp": "2020-10-05T18:25:15+00:00",
    "added": [
      "",
      "From 1976 through 1978, he worked as an economist for the company Coilcraft.<ref name=berkman1/>"
    ],
    "deleted": []
  }
]