[
  {
    "title": "2021 Virginia gubernatorial election",
    "timestamp": "2020-09-03T03:32:53+00:00",
    "added": [],
    "deleted": [
      "*[[Eileen Filler-Corn]], [[Speaker of the Virginia House of Delegates]]<ref name=\"Pisani\"/>",
      "*[[Abigail Spanberger]], U.S. Representative for [[Virginia's 7th congressional district]]<ref name=\"Pisani\"/>"
    ]
  },
  {
    "title": "2021 Virginia gubernatorial election",
    "timestamp": "2020-10-08T23:13:47+00:00",
    "added": [],
    "deleted": [
      "* DJ Jordan, Never-Trumper, Moderate Republican, and 2019 candidate for House of Delegates."
    ]
  }
]