[
  {
    "title": "Prince George's County, Maryland",
    "timestamp": "2021-01-10T22:47:48+00:00",
    "added": [],
    "deleted": [
      "]"
    ]
  },
  {
    "title": "Prince George's County, Maryland",
    "timestamp": "2021-01-10T22:48:28+00:00",
    "added": [],
    "deleted": [
      ""
    ]
  },
  {
    "title": "Prince George's County, Maryland",
    "timestamp": "2022-04-02T13:23:37+00:00",
    "added": [
      "*[[Maryland Park, Maryland|Maryland Park]]"
    ],
    "deleted": []
  },
  {
    "title": "Prince George's County, Maryland",
    "timestamp": "2022-04-17T22:57:43+00:00",
    "added": [],
    "deleted": [
      "",
      "==Notes==",
      "{{notelist}}"
    ]
  },
  {
    "title": "Prince George's County, Maryland",
    "timestamp": "2022-07-25T12:04:20+00:00",
    "added": [
      "*[[Walt Simonson]], comic book writer and artist, best known for his mid-1980s run on Marvel Comics' ''Thor'', grew up in the [[Calvert Hills Historic District|Calvert Hills]] section of College Park."
    ],
    "deleted": []
  },
  {
    "title": "Prince George's County, Maryland",
    "timestamp": "2022-08-14T03:16:29+00:00",
    "added": [],
    "deleted": [
      "",
      "====Inner Beltway====",
      "The inner beltway communities of [[Capitol Heights, Maryland|Capitol Heights]], [[District Heights, Maryland|District Heights]], [[Fairmount Heights, Maryland|Fairmont Heights]], [[Forestville, Maryland|Forestville]], [[Suitland, Maryland|Suitland]], and [[Seat Pleasant, Maryland|Seat Pleasant]] border the neighboring District of Columbia's northeastern and southeastern quadrants. The area has easy access to [[Blue Line (Washington Metro)|Metro's blue line]], commercial centers, Maryland Route 214, Interstate 95/Interstate 495 (Capital Beltway). Protected bike trails connect residents to the Bladensburg waterfront, Kenilworth parks, and downtown D.C. Fairmont Heights is the second oldest African-American-majority municipality in Prince George's County. The Fairmount Heights Historic District was added to the National Register of Historic Places in 2011.<ref>{{cite news|last1=Downs|first1=Kat|last2=Keating|first2=Dan|last3=Vaughn Kelso|first3=Nathaniel|title=Segregation Receding|url=https://www.washingtonpost.com/wp-srv/special/nation/census/2010/?custommap=0,4,2,0,38.89511,-77.0363,11,0|work=The Washington Post|access-date=November 2, 2011|archive-date=September 4, 2015|archive-url=https://web.archive.org/web/20150904044041/http://www.washingtonpost.com/wp-srv/special/nation/census/2010/?custommap=0,4,2,0,38.89511,-77.0363,11,0|url-status=dead}}</ref>"
    ]
  },
  {
    "title": "Prince George's County, Maryland",
    "timestamp": "2022-08-14T03:18:21+00:00",
    "added": [],
    "deleted": []
  },
  {
    "title": "Prince George's County, Maryland",
    "timestamp": "2023-09-02T04:04:18+00:00",
    "added": [
      "|194,836",
      "|24.31%",
      "|498,301",
      "|62.17%",
      "|2,274",
      "|0.28%",
      "|30,803",
      "|3.84%",
      "|318",
      "|0.04%",
      "|1,706",
      "|0.21%",
      "|16,220",
      "|2.02%",
      "|57,057",
      "|7.12%",
      "|'''801,515'''"
    ],
    "deleted": []
  },
  {
    "title": "Prince George's County, Maryland",
    "timestamp": "2024-02-05T22:43:59+00:00",
    "added": [
      "*[[Brown Station, Maryland|Brown Station]]"
    ],
    "deleted": []
  },
  {
    "title": "Prince George's County, Maryland",
    "timestamp": "2024-06-19T00:47:48+00:00",
    "added": [],
    "deleted": [
      "*[[Tony Lewis Sr]], was a Notorious D.C. drug kingpin who lived in Largo, Maryland.}}<ref>{{Cite book |last=Lewis |first=Tony |title=Slugg \"a boy's life in the age of mass incarceration\" |date=January 10, 2024 |publisher=Hanover place press |year=2015 |isbn=978-152-1308-783 |edition=First |location=Washington DC |publication-date=July 30, 2015 |pages=9 |language=English |trans-title=English}}</ref>"
    ]
  },
  {
    "title": "Prince George's County, Maryland",
    "timestamp": "2024-08-01T04:45:47+00:00",
    "added": [],
    "deleted": []
  },
  {
    "title": "Prince George's County, Maryland",
    "timestamp": "2024-12-04T08:44:31+00:00",
    "added": [],
    "deleted": [
      "*[https://ghostsofdc.org/2013/07/03/detailed-1861-map-of-prince-georges-county/ Detailed 1861 Map of Prince Georges County] – Ghosts of DC blog"
    ]
  },
  {
    "title": "Prince George's County, Maryland",
    "timestamp": "2025-02-12T15:43:39+00:00",
    "added": [
      "*[[Forestville, Maryland]]"
    ],
    "deleted": []
  },
  {
    "title": "Prince George's County, Maryland",
    "timestamp": "2025-02-12T15:45:09+00:00",
    "added": [
      "*[[Forestville]]"
    ],
    "deleted": []
  }
]