[
  {
    "title": "Political career of Donald Trump",
    "timestamp": "2022-03-10T05:05:09+00:00",
    "added": [],
    "deleted": []
  },
  {
    "title": "Political career of Donald Trump",
    "timestamp": "2022-06-05T23:24:52+00:00",
    "added": [],
    "deleted": [
      ""
    ]
  },
  {
    "title": "Political career of Donald Trump",
    "timestamp": "2022-10-17T03:13:42+00:00",
    "added": [
      "",
      "There are currently four major ongoing criminal investigations into Trump’s criminal activity while in office.  <ref> https://www.vox.com/platform/amp/policy-and-politics/23306941/donald-trump-crimes-criminal-investigation-mar-a-lago-fbi-january-6-election-georgia-new-york </ref>"
    ],
    "deleted": []
  },
  {
    "title": "Political career of Donald Trump",
    "timestamp": "2022-11-16T02:11:37+00:00",
    "added": [
      "{{pp-protected|reason=Persistent [[WP:Disruptive editing|disruptive editing]]|small=yes}}"
    ],
    "deleted": []
  },
  {
    "title": "Political career of Donald Trump",
    "timestamp": "2023-06-17T03:28:40+00:00",
    "added": [
      "{{Update|date=June 2023}}"
    ],
    "deleted": []
  },
  {
    "title": "Political career of Donald Trump",
    "timestamp": "2023-09-06T02:03:39+00:00",
    "added": [
      "",
      "==Cited works==",
      "* {{cite book |url=https://books.google.com/books?id=G7Tf_1GzlHEC |title=The Gallup Poll: Public Opinion 1989 |last=Gallup |first=George Jr. |authorlink=George Gallup Jr. |publisher=[[Rowman & Littlefield]] |year=1990 |isbn=978-0-8420-2344-3}}",
      "* {{cite book |title=Trump Revealed: The Definitive Biography of the 45th President |last1=Kranish |first1=Michael |author1link=Michael Kranish |last2=Fisher |first2=Marc |author2link=Marc Fisher |publisher=[[Simon & Schuster]] |year=2017 |orig-year=First published 2016 |isbn=978-1-5011-5652-6 |title-link=Trump Revealed}}",
      "* {{cite book |url=https://books.google.com/books?id=Ye6e_VxM00kC |title=Trump: The Art of the Deal |first1=Donald J. |last1=Trump |first2=Tony |last2=Schwartz |author2link=Tony Schwartz (author) |publisher=[[Random House]] |year=2009 |orig-year=First published 1987 |isbn=978-0-446-35325-0 }}",
      ""
    ],
    "deleted": []
  },
  {
    "title": "Political career of Donald Trump",
    "timestamp": "2023-10-06T18:35:15+00:00",
    "added": [
      "{{pp-extended|small=yes}}"
    ],
    "deleted": []
  },
  {
    "title": "Political career of Donald Trump",
    "timestamp": "2024-11-06T12:49:56+00:00",
    "added": [],
    "deleted": []
  },
  {
    "title": "Political career of Donald Trump",
    "timestamp": "2024-11-06T17:51:00+00:00",
    "added": [
      "On 15 July 2024 the [[Republican Party (United States)|United States Republican Party]] selected the party's nominees for [[President of the United States|president]] and [[Vice President of the United States|vice president]] in the [[2024 United States presidential election]].<ref>{{Cite web|url=https://thehill.com/homenews/campaign/4771940-rnc-trump-2024-live-updates/https://thehill.com/homenews/campaign/4771940-rnc-trump-2024-live-updates/|title=Live updates: Trump picks JD Vance for VP as he clinches nomination |website=The Hill|date=July 15, 2024}}<ref>"
    ],
    "deleted": []
  },
  {
    "title": "Political career of Donald Trump",
    "timestamp": "2024-11-06T18:01:10+00:00",
    "added": [
      "On 15 July 2024,the [[Republican Party (United States)|United States Republican Party]] selectedTrump and JD Vancethe party's nominees for [[President of the United States|president]] and [[Vice President of the United States|vice president]] in the [[2024 United States presidential election]].<ref>https://www.theguardian.com/us-news/article/2024/jul/15/trump-milwaukee-republican-national-convention</ref>"
    ],
    "deleted": []
  },
  {
    "title": "Political career of Donald Trump",
    "timestamp": "2024-11-06T18:50:12+00:00",
    "added": [],
    "deleted": [
      "{{Main|Presidency of Donald Trump}}"
    ]
  },
  {
    "title": "Political career of Donald Trump",
    "timestamp": "2025-03-26T07:37:47+00:00",
    "added": [
      "",
      "Trump’s involvement in politics began in the late 1970s and early 80s when he donated to the presidential campaigns of Ronald Reagan, Jimmy Carter, and later a PAC affiliated with Walter Mondale. Between 1982 and 1985, he would be involved in fundraising and financing for the Vietnam Veterans Plaza as co-chair of the Vietnam Veterans Memorial Commission, hosting of the 1983 National Awards Banquet Dinner as a special advisor to the President’s Council on Physical Fitness and Sport, and overseeing the body’s work and fundraising activities."
    ],
    "deleted": []
  }
]