[
  {
    "title": "Mary Miller (politician)",
    "timestamp": "2021-01-03T19:40:56+00:00",
    "added": [
      "{{s-inc}}<!--"
    ],
    "deleted": []
  },
  {
    "title": "Mary Miller (politician)",
    "timestamp": "2021-01-06T18:57:07+00:00",
    "added": [],
    "deleted": [
      ""
    ]
  },
  {
    "title": "Mary Miller (politician)",
    "timestamp": "2021-01-06T22:17:03+00:00",
    "added": [
      "[[Category:Antisemitism in the United States]]"
    ],
    "deleted": []
  },
  {
    "title": "Mary Miller (politician)",
    "timestamp": "2021-01-06T22:28:33+00:00",
    "added": [],
    "deleted": [
      "[[Category:Antisemitism in the United States]]"
    ]
  },
  {
    "title": "Mary Miller (politician)",
    "timestamp": "2021-01-08T18:33:23+00:00",
    "added": [],
    "deleted": [
      "=== 2020 presidential election ==="
    ]
  },
  {
    "title": "Mary Miller (politician)",
    "timestamp": "2021-01-09T23:27:09+00:00",
    "added": [
      "<ref>https://fox2now.com/news/national/lawmakers-demand-apology-resignation-from-ill-congresswomans-hitler-comment/</ref>"
    ],
    "deleted": []
  },
  {
    "title": "Mary Miller (politician)",
    "timestamp": "2021-01-09T23:29:00+00:00",
    "added": [],
    "deleted": [
      "<ref><ref></ref></ref>{{short description|American politician}}"
    ]
  },
  {
    "title": "Mary Miller (politician)",
    "timestamp": "2021-01-10T02:12:30+00:00",
    "added": [],
    "deleted": [
      "",
      "Mary Miller is a proud supporter of National Socialism."
    ]
  },
  {
    "title": "Mary Miller (politician)",
    "timestamp": "2021-01-21T18:16:36+00:00",
    "added": [
      "* [[Sedition Caucus]]"
    ],
    "deleted": []
  },
  {
    "title": "Mary Miller (politician)",
    "timestamp": "2021-01-21T18:18:43+00:00",
    "added": [
      "* [[Sedition Caucus]]<ref>https://theseditioncaucus.org/</ref>"
    ],
    "deleted": []
  }
]