[
  {
    "title": "Ulrich Brechbuhl",
    "timestamp": "2021-01-26T15:06:05+00:00",
    "added": [
      "[[Category:United States Under Secretaries of State]]"
    ],
    "deleted": []
  },
  {
    "title": "Ulrich Brechbuhl",
    "timestamp": "2021-02-05T22:16:25+00:00",
    "added": [
      "| allegiance          = {{flag|United States}}",
      "| branch              = {{army|United States}}",
      "| unit                =",
      "| serviceyears        = 1986-1992",
      "| battles             ="
    ],
    "deleted": []
  }
]