[
  {
    "title": "2021 New Mexico's 1st congressional district special election",
    "timestamp": "2021-01-05T18:11:28+00:00",
    "added": [],
    "deleted": [
      "*[[Georgene Louis]], state representative<ref name=\":4\" />"
    ]
  },
  {
    "title": "2021 New Mexico's 1st congressional district special election",
    "timestamp": "2021-01-09T09:21:52+00:00",
    "added": [
      "* [[Tim Eichenberg]], [[New Mexico State Treasurer]]"
    ],
    "deleted": []
  },
  {
    "title": "2021 New Mexico's 1st congressional district special election",
    "timestamp": "2021-01-11T15:10:52+00:00",
    "added": [
      "* [https://www.victorreyes.org/ Victor Reyes (D) for Congress]"
    ],
    "deleted": []
  },
  {
    "title": "2021 New Mexico's 1st congressional district special election",
    "timestamp": "2021-01-16T03:30:43+00:00",
    "added": [
      "* [https://www.mcginnfornm.com/ Randi McGinn (D) for Congress]"
    ],
    "deleted": []
  },
  {
    "title": "2021 New Mexico's 1st congressional district special election",
    "timestamp": "2021-01-24T06:52:54+00:00",
    "added": [
      "{{Endorsements box",
      "|list=",
      "; State legislators",
      "* [[Anthony Allison (politician)|Anthony Allison]], Member of the [[New Mexico House of Representatives]] from District 4 (2019-present)<ref>https://www.facebook.com/tony.allison.1213/posts/687996535223642</ref>",
      "* [[Gail Chasey]], Member of the [[New Mexico House of Representatives]] from District 18 (1997-present)<ref>https://www.facebook.com/repchasey/posts/4933694343368975</ref>",
      "}}"
    ],
    "deleted": []
  },
  {
    "title": "2021 New Mexico's 1st congressional district special election",
    "timestamp": "2021-01-24T06:55:22+00:00",
    "added": [
      "* [[Anthony Allison (politician)|Anthony Allison]], Member of the [[New Mexico House of Representatives]] from District 4 (2019–present)<ref>https://www.facebook.com/tony.allison.1213/posts/687996535223642</ref>",
      "* [[Gail Chasey]], Member of the [[New Mexico House of Representatives]] from District 18 (1997–present)<ref>https://www.facebook.com/repchasey/posts/4933694343368975</ref>"
    ],
    "deleted": []
  },
  {
    "title": "2021 New Mexico's 1st congressional district special election",
    "timestamp": "2021-01-25T04:11:57+00:00",
    "added": [],
    "deleted": [
      "*Selinda Guerrero, community organizer"
    ]
  },
  {
    "title": "2021 New Mexico's 1st congressional district special election",
    "timestamp": "2021-01-25T04:51:12+00:00",
    "added": [],
    "deleted": [
      "*Selinda Guerrero, Frontline Community Organizer"
    ]
  },
  {
    "title": "2021 New Mexico's 1st congressional district special election",
    "timestamp": "2021-01-25T04:51:55+00:00",
    "added": [
      "*Selinda Guerrero, community organizer"
    ],
    "deleted": []
  },
  {
    "title": "2021 New Mexico's 1st congressional district special election",
    "timestamp": "2021-01-25T05:21:39+00:00",
    "added": [],
    "deleted": [
      "*Selinda Guerrero, community organizer"
    ]
  },
  {
    "title": "2021 New Mexico's 1st congressional district special election",
    "timestamp": "2021-01-25T23:27:06+00:00",
    "added": [],
    "deleted": [
      "*[[Draft:Selinda Guerrero|Selinda Guererro]], community organizer"
    ]
  },
  {
    "title": "2021 New Mexico's 1st congressional district special election",
    "timestamp": "2021-02-07T17:35:12+00:00",
    "added": [
      "* Selinda Guerrero, community organizer<ref>{{cite web |last1=McKee |first1=Chris |title=Special Election: 1st Congressional District – Who’s Running? |url=https://www.krqe.com/news/politics-government/elections/new-mexicos-1st-congressional-district-special-election/ |website=www.krqe.com |publisher=[[KRQE]] |date=January 11, 2021}}</ref>"
    ],
    "deleted": []
  },
  {
    "title": "2021 New Mexico's 1st congressional district special election",
    "timestamp": "2021-02-12T05:43:03+00:00",
    "added": [],
    "deleted": [
      "* [[Roberto Gonzales]], Member of the [[New Mexico House of Representatives]] from District 6 (2019–present)<ref>https://www.facebook.com/AntoinetteforNM/posts/1080102492459296</ref>"
    ]
  },
  {
    "title": "2021 New Mexico's 1st congressional district special election",
    "timestamp": "2021-02-12T05:54:01+00:00",
    "added": [
      "* Our Revolution New Mexico<ref>{{cite web|title=As most of you know, Rep. Deb Haaland has been nominated for Interior Secretary. This will leave her seat in the House of Representatives open. We want Progressive Antoinette Sedillo Lopez to fill that seat!|url=https://www.facebook.com/RevolutionNM/posts/1588228684697179|publisher=Facebook|date=February 11, 2021|access-date=February 11, 2021}}</ref>"
    ],
    "deleted": []
  },
  {
    "title": "2021 New Mexico's 1st congressional district special election",
    "timestamp": "2021-02-12T06:10:17+00:00",
    "added": [
      "*[[Our Revolution]]New Mexico<ref>{{cite web|title=As most of you know, Rep. Deb Haaland has been nominated for Interior Secretary. This will leave her seat in the House of Representatives open. We want Progressive Antoinette Sedillo Lopez to fill that seat!|url=https://www.facebook.com/RevolutionNM/posts/1588228684697179|publisher=Facebook|date=February 11, 2021|access-date=February 11, 2021}}</ref>"
    ],
    "deleted": []
  },
  {
    "title": "2021 New Mexico's 1st congressional district special election",
    "timestamp": "2021-02-12T21:25:44+00:00",
    "added": [],
    "deleted": [
      "* Matriarch PAC<ref>{{cite tweet|user=MatriarchOrg |number=1354474849503223812 |date=January 27, 2021 |title=We are thrilled to announce our first endorsement of 2021: State Senator Antoinette Sedillo Lopez in NM-01. She cares deeply about our planet and is a true, tireless champion for working class people and our environment. Welcome to the Matriarch sisterhood, @ASL4Justice4all! |language=en |access-date=January 27, 2021 |url=https://twitter.com/MatriarchOrg/status/1354474849503223812}}</ref>"
    ]
  },
  {
    "title": "2021 New Mexico's 1st congressional district special election",
    "timestamp": "2021-02-12T21:27:57+00:00",
    "added": [
      "{{Short description|Special election for United States Congress from New Mexico}}"
    ],
    "deleted": []
  },
  {
    "title": "2021 New Mexico's 1st congressional district special election",
    "timestamp": "2021-02-24T00:02:16+00:00",
    "added": [
      "*[[David Cicilline]], [[United States House of Representatives|U.S. Representative]] from [[Rhode Island's 1st congressional district]] (2011–present)<ref> https://mobile.twitter.com/vicrreyes/status/1362907315888787456</ref>",
      "*[[Mark Takano]], [[United States House of Representatives|U.S. Representative]] from [[California's 41st congressional district]] (2013–present)<ref> https://mobile.twitter.com/vicrreyes/status/1362907315888787456</ref>"
    ],
    "deleted": []
  },
  {
    "title": "2021 New Mexico's 1st congressional district special election",
    "timestamp": "2021-02-24T00:05:47+00:00",
    "added": [],
    "deleted": [
      ";U.S. Representatives",
      "*[[David Cicilline]], [[United States House of Representatives|U.S. Representative]] from [[Rhode Island's 1st congressional district]] (2011–present)<ref> https://mobile.twitter.com/vicrreyes/status/1362907315888787456</ref>",
      "*[[Mark Takano]], [[United States House of Representatives|U.S. Representative]] from [[California's 41st congressional district]] (2013–present)<ref> https://mobile.twitter.com/vicrreyes/status/1362907315888787456</ref>",
      "*[[Ritchie Torres]], [[United States House of Representatives|U.S. Representative]] from [[New York's 15th congressional district]] (2021–present)<ref> https://mobile.twitter.com/vicrreyes/status/1364243620539232258</ref>",
      ";State legislators",
      "*[[Leo Jaramillo]], [[New Mexico Senate|New Mexico State Senator]] from District 5 (2021–present)<ref> https://mobile.twitter.com/vicrreyes/status/1362922416394039298</ref>"
    ]
  },
  {
    "title": "2021 New Mexico's 1st congressional district special election",
    "timestamp": "2021-03-18T21:11:18+00:00",
    "added": [],
    "deleted": [
      "*Elisa Martinez, Pro-Life Activist and 2018 Candidate for [[United States Senate]]"
    ]
  },
  {
    "title": "2021 New Mexico's 1st congressional district special election",
    "timestamp": "2021-03-27T19:38:46+00:00",
    "added": [],
    "deleted": [
      "",
      "====Declined====",
      "*[[Javier Martínez (politician)|Javier Martínez]], [[New Mexico House of Representatives|state representative]]<ref name=\":5\"/>",
      "*[[Maggie Toulouse Oliver]], [[New Mexico Secretary of State]]<ref name=\":4\"/>"
    ]
  },
  {
    "title": "2021 New Mexico's 1st congressional district special election",
    "timestamp": "2021-03-27T19:39:10+00:00",
    "added": [],
    "deleted": []
  },
  {
    "title": "2021 New Mexico's 1st congressional district special election",
    "timestamp": "2021-03-27T21:06:04+00:00",
    "added": [],
    "deleted": [
      "",
      "===Declined===",
      "*Mark Ronchetti, former [[KRQE]] chief [[meteorologist]] and nominee for U.S. Senate in [[2020 United States Senate election in New Mexico|2020]]<ref name=\":3\"/><ref name=\":1\"/>"
    ]
  },
  {
    "title": "2021 New Mexico's 1st congressional district special election",
    "timestamp": "2021-03-27T23:30:21+00:00",
    "added": [
      "",
      "====Results===="
    ],
    "deleted": []
  },
  {
    "title": "2021 New Mexico's 1st congressional district special election",
    "timestamp": "2021-03-28T10:10:47+00:00",
    "added": [
      "| candidate3         = [[Aubrey Dunn Jr.]]",
      "| party3             = Independent (politican)"
    ],
    "deleted": []
  },
  {
    "title": "2021 New Mexico's 1st congressional district special election",
    "timestamp": "2021-03-29T23:13:43+00:00",
    "added": [
      "{{Endorsements box",
      "|list=",
      ";Organizations",
      "* All Pueblo Council of Governors (APCG)<ref>{{cite web|url=https://nativenewsonline.net/currents/all-pueblo-council-of-governors-backs-georgene-louis-to-fill-congressional-seat-vacated-by-deb-haaland|title=All Pueblo Council of Governors Backs Georgene Louis to Fill Congressional Seat Vacated by Deb Haaland|date=March 29, 2021}}</ref>",
      "}}",
      ""
    ],
    "deleted": []
  },
  {
    "title": "2021 New Mexico's 1st congressional district special election",
    "timestamp": "2021-03-29T23:18:08+00:00",
    "added": [
      "* All Pueblo Council of Governors (APCG)<refname=\"Native News\">{{cite web|url=https://nativenewsonline.net/currents/all-pueblo-council-of-governors-backs-georgene-louis-to-fill-congressional-seat-vacated-by-deb-haaland|title=All Pueblo Council of Governors Backs Georgene Louis to Fill Congressional Seat Vacated by Deb Haaland|date=March 29, 2021}}</ref>",
      "* Coalition of Large Tribes (COLT)<ref name=\"Native News\"></ref>",
      "* Midwest Alliance of Sovereign Tribes (MAST)<ref name=\"Native News\"></ref>"
    ],
    "deleted": []
  },
  {
    "title": "2021 New Mexico's 1st congressional district special election",
    "timestamp": "2021-03-30T03:34:29+00:00",
    "added": [
      "}}",
      "",
      "{{Endorsements box",
      "|list=",
      ";Organizations",
      "* [[American Federation of State, County and Municipal Employees]]<ref name=\"NMPJ\"></ref>",
      "* [[Sierra Club]]<ref name=\"NMPJ\">{{cite web|url=https://www.newmexicopoliticaljournal.com/default.aspx?f8c38a75aa484b4dbf205c150d8d029fblogPostId=0423ba66475f445c99018d91fb122fe7|title=New Mexico Democrats Set to Choose Their CD 1 Nominee: A Look at the Candidates and a Discussion of the Internal Politics|date=March 29, 2021}}</ref>"
    ],
    "deleted": []
  },
  {
    "title": "2021 New Mexico's 1st congressional district special election",
    "timestamp": "2021-03-30T18:29:16+00:00",
    "added": [],
    "deleted": [
      "* [https://www.elisafornm.com Elisa Martinez (R) for Congress]"
    ]
  },
  {
    "title": "2021 New Mexico's 1st congressional district special election",
    "timestamp": "2021-03-31T02:17:54+00:00",
    "added": [
      "|colspan=\"2\"bgcolor=\"lightgray\"align=\"center\"|''Eliminated''",
      "|colspan=\"2\"bgcolor=\"lightgray\"align=\"center\"|''Eliminated''",
      "|colspan=\"2\"bgcolor=\"lightgray\"align=\"center\"|''Eliminated''",
      "|colspan=\"2\"bgcolor=\"lightgray\"align=\"center\"|''Eliminated''",
      "|colspan=\"2\"bgcolor=\"lightgray\"align=\"center\"|''Eliminated''",
      "|colspan=\"2\"bgcolor=\"lightgray\"align=\"center\"|''Eliminated''",
      "|colspan=\"2\"bgcolor=\"lightgray\"align=\"center\"|''Eliminated''"
    ],
    "deleted": []
  },
  {
    "title": "2021 New Mexico's 1st congressional district special election",
    "timestamp": "2021-04-01T02:05:53+00:00",
    "added": [
      "=== Results ===",
      "{{Election box begin no change|title=New Mexico's 1st congressional district special election, 2021}}",
      "{{Election box candidate with party link no change|candidate=[[Melanie Stansbury]]|party=Democratic Party (United States)|votes=|percentage=}}",
      "{{Election box candidate with party link no change|candidate=[[Mark Moores]]|party=Republican Party (United States)|votes=|percentage=}}",
      "{{Election box candidate with party link no change|candidate=[[Aubrey Dunn Jr.]]|party=Independent politician|votes=|percentage=}}",
      "{{Election box candidate with party link no change|candidate=Chris Manning|party=Libertarian Party (United States)|votes=|percentage=}}",
      "",
      "{{Election box total no change|votes=|percentage=100.00}}",
      "{{Election box end}}"
    ],
    "deleted": []
  }
]