[
  {
    "title": "Robert Biedroń",
    "timestamp": "2021-02-20T02:28:56+00:00",
    "added": [],
    "deleted": [
      "",
      "Bedron is known for lying to the European Parlament about the alleged incident, in which he was supposedly declined dining in one of the restaurants, because of his sexual orientation. Biedron made up the story."
    ]
  },
  {
    "title": "Robert Biedroń",
    "timestamp": "2021-02-20T02:36:17+00:00",
    "added": [],
    "deleted": [
      "",
      "Biedron is best known for lying to the European Parlament in regards to being denied dining in Poland,",
      "because of his sexual orientation.  Biedron made up the story."
    ]
  },
  {
    "title": "Robert Biedroń",
    "timestamp": "2021-02-20T02:36:34+00:00",
    "added": [],
    "deleted": []
  },
  {
    "title": "Robert Biedroń",
    "timestamp": "2021-02-20T02:38:34+00:00",
    "added": [],
    "deleted": [
      "",
      "Biedron is best known for lying to the European Parlament in regards to being denied dining in Poland,",
      "because of his sexual orientation.  Biedron made up the story."
    ]
  },
  {
    "title": "Robert Biedroń",
    "timestamp": "2021-02-20T02:38:50+00:00",
    "added": [],
    "deleted": []
  },
  {
    "title": "Robert Biedroń",
    "timestamp": "2021-02-20T02:39:38+00:00",
    "added": [],
    "deleted": [
      "",
      "Biedron is best known for lying to the European Parlament in regards to being denied dining in Poland,",
      "because of his sexual orientation.  Biedron made up the story.",
      "",
      ""
    ]
  },
  {
    "title": "Robert Biedroń",
    "timestamp": "2021-02-20T02:40:07+00:00",
    "added": [],
    "deleted": []
  },
  {
    "title": "Robert Biedroń",
    "timestamp": "2021-02-20T02:40:59+00:00",
    "added": [],
    "deleted": [
      "",
      "Biedron is best known for lying to the European Parlament in regards to being denied dining in Poland,",
      "because of his sexual orientation.  Biedron made up the story."
    ]
  }
]