[
  {
    "title": "Congressional Progressive Caucus",
    "timestamp": "2021-01-25T16:33:47+00:00",
    "added": [],
    "deleted": [
      "<!——- Removing reliably sourced content will result in an immediate revert. ——-!>"
    ]
  },
  {
    "title": "Congressional Progressive Caucus",
    "timestamp": "2021-02-09T03:51:49+00:00",
    "added": [],
    "deleted": [
      "",
      "In October 2020, members were sent a number of changes to the caucus’s leadership structure and to membership requirements, on which to vote.<ref>{{Cite web|last=Grim|first=Ryan|date=October 26, 2020|title=Congressional Progressives Are Revamping Their Caucus With an Eye Toward 2021|url=https://theintercept.com/2020/10/26/congressional-progressives-are-revamping-their-caucus-with-an-eye-toward-2021/|access-date=2021-01-04|website=The Intercept|language=en}}</ref>"
    ]
  },
  {
    "title": "Congressional Progressive Caucus",
    "timestamp": "2021-02-14T03:04:04+00:00",
    "added": [],
    "deleted": [
      "| seats1_title = Seats in the [[United States Senate|Senate]] Democratic Caucus",
      "| seats1 = {{composition bar|1|50|hex=#003366}}",
      "| seats2_title = Seats in the [[United States Senate|Senate]]",
      "| seats2 = {{composition bar|1|100|hex=#003366}}"
    ]
  },
  {
    "title": "Congressional Progressive Caucus",
    "timestamp": "2021-03-10T21:28:16+00:00",
    "added": [
      "| logo_size = 125px"
    ],
    "deleted": []
  },
  {
    "title": "Congressional Progressive Caucus",
    "timestamp": "2021-03-10T21:28:47+00:00",
    "added": [
      "| logo_size =100px"
    ],
    "deleted": []
  },
  {
    "title": "Congressional Progressive Caucus",
    "timestamp": "2021-03-10T23:34:06+00:00",
    "added": [
      "| logo_size = 100px"
    ],
    "deleted": []
  }
]