[
  {
    "title": "2022 Oklahoma House of Representatives election",
    "timestamp": "2021-03-23T18:00:10+00:00",
    "added": [
      "",
      "==See also==",
      "",
      "==References==",
      "{{Reflist}}"
    ],
    "deleted": []
  },
  {
    "title": "2022 Oklahoma House of Representatives election",
    "timestamp": "2021-03-23T19:20:21+00:00",
    "added": [],
    "deleted": []
  },
  {
    "title": "2022 Oklahoma House of Representatives election",
    "timestamp": "2021-03-23T19:20:55+00:00",
    "added": [],
    "deleted": []
  },
  {
    "title": "2022 Oklahoma House of Representatives election",
    "timestamp": "2021-03-30T17:23:59+00:00",
    "added": [],
    "deleted": []
  }
]