[
  {
    "title": "1900 United States House of Representatives elections",
    "timestamp": "2021-02-24T17:13:52+00:00",
    "added": [
      "",
      "== New Hampshire ==",
      "",
      "== New Jersey ==",
      "",
      "== New York ==",
      "",
      "== North Carolina ==",
      "",
      "== North Dakota ==",
      "",
      "== Ohio ==",
      "",
      "== Oregon ==",
      "",
      "== Pennsylvania ==",
      "",
      "== Rhode Island =="
    ],
    "deleted": []
  },
  {
    "title": "1900 United States House of Representatives elections",
    "timestamp": "2021-02-24T17:19:38+00:00",
    "added": [],
    "deleted": [
      ""
    ]
  }
]