[
  {
    "title": "John Jay",
    "timestamp": "2021-02-20T23:07:34+00:00",
    "added": [],
    "deleted": [
      "",
      "====Education====",
      "",
      "The John Jay Institute, located outside Philadelphia, is the only independent faith-based organization in America exclusively dedicated to preparing principled leaders for public service. Their website is https://www.johnjayfellows.com/"
    ]
  },
  {
    "title": "John Jay",
    "timestamp": "2021-02-20T23:11:11+00:00",
    "added": [],
    "deleted": []
  }
]